snake_charmer/__init__.py
snake_charmer/tools/__init__.py
snake_charmer/tools/snake_charmer_docs.py
snake_charmer/tools/utils.py
snake_charmer/yamls/snake_charmer_docs.yaml
tests/__init__.py
tests/test_snake_charmer_docs.py
snake_charmer_pftools-0.0.1.dist-info/METADATA
snake_charmer_pftools-0.0.1.dist-info/WHEEL
snake_charmer_pftools-0.0.1.dist-info/entry_points.txt
snake_charmer_pftools-0.0.1.dist-info/top_level.txt
snake_charmer_pftools-0.0.1.dist-info/RECORD
