Metadata-Version: 2.1
Name: snake-charmer-pftools
Version: 0.0.1
Summary: Snake Charmer PFTOOLS
